cgd_validator/__init__.py
cgd_validator/cli.py
cgd_validator-0.1.1.dist-info/METADATA
cgd_validator-0.1.1.dist-info/WHEEL
cgd_validator-0.1.1.dist-info/entry_points.txt
cgd_validator-0.1.1.dist-info/RECORD
