Metadata-Version: 2.4
Name: cgd-validator
Version: 0.1.1
Summary: Validator for Clarity-Gated Document (.cgd) files - verified documents for safe LLM ingestion
Project-URL: Homepage, https://github.com/frmoretto/clarity-gate
Project-URL: Repository, https://github.com/frmoretto/cgd-validator
Project-URL: Documentation, https://github.com/frmoretto/clarity-gate/blob/main/docs/FILE_FORMAT_SPEC.md
Project-URL: Issues, https://github.com/frmoretto/clarity-gate/issues
Author-email: Francesco Marinoni Moretto <francesco@fmmconsulting.it>
License-Expression: CC-BY-4.0
Keywords: ai-safety,cgd,clarity-gate,documentation,epistemic,llm,rag,validator,verification
Classifier: Development Status :: 3 - Alpha
Classifier: Intended Audience :: Developers
Classifier: Programming Language :: Python :: 3
Classifier: Programming Language :: Python :: 3.9
Classifier: Programming Language :: Python :: 3.10
Classifier: Programming Language :: Python :: 3.11
Classifier: Programming Language :: Python :: 3.12
Classifier: Topic :: Documentation
Classifier: Topic :: Scientific/Engineering :: Artificial Intelligence
Requires-Python: >=3.9
